cloud_containers/.DS_Store
cloud_containers/__init__.py
cloud_containers/build/__init__.py
cloud_containers/deploy/__init__.py
cloud_containers-0.1.2.dist-info/WHEEL
cloud_containers-0.1.2.dist-info/METADATA
cloud_containers-0.1.2.dist-info/RECORD
