Metadata-Version: 2.1
Name: cloud-containers
Version: 0.1.2
Summary: A Python Package for Building and Deploying Containers
Author: Ryan Moos
Author-email: ryan@moos.engineering
Requires-Python: >=3.9,<4.0
Classifier: Programming Language :: Python :: 3
Classifier: Programming Language :: Python :: 3.10
Classifier: Programming Language :: Python :: 3.9
Requires-Dist: cdk8s (>=2.3.77,<3.0.0)
Requires-Dist: cdk8s-plus-22 (>=2.0.0-rc.75,<3.0.0)
Requires-Dist: constructs (>=10.1.69,<11.0.0)
Requires-Dist: docker (>=5.0.3,<6.0.0)
